ebook_extractor/__init__.py
ebook_extractor/emulation/__init__.py
ebook_extractor/emulation/book.py
ebook_extractor/emulation/types.py
ebook_extractor/export/__init__.py
ebook_extractor/export/images.py
ebook_extractor/export/pdf.py
ebook_extractor/prototype/__init__.py
ebook_extractor/prototype/book.py
ebook_extractor_cli/__entry__.py
ebook_extractor_cli/__init__.py
ebook_extractor_cli/__main__.py
ebook_extractor-1.0.0.dist-info/METADATA
ebook_extractor-1.0.0.dist-info/WHEEL
ebook_extractor-1.0.0.dist-info/entry_points.txt
ebook_extractor-1.0.0.dist-info/licenses/LICENSE
ebook_extractor-1.0.0.dist-info/RECORD
